<?xml version="1.0" encoding="utf-8"?>
<!DOCTYPE hibernate-mapping PUBLIC "-//Hibernate/Hibernate Mapping DTD 3.0//EN"
                                   "http://hibernate.sourceforge.net/hibernate-mapping-3.0.dtd">
<!-- 
    Mapping file autogenerated by MyEclipse Persistence Tools
-->
<hibernate-mapping>
 <class catalog="biye" name="org.hch.yhw.auction.model.Item" table="item">
  <id name="id" type="integer">
   <column name="item_id"/>
   <generator class="increment"/>
  </id>
  <many-to-one class="org.hch.yhw.auction.model.Admin" lazy="false" name="owner">
   <column name="owner_id"/>
  </many-to-one>
  <many-to-one class="org.hch.yhw.auction.model.State" lazy="false" name="itemState">
   <column name="state_id"/>
  </many-to-one>
  <many-to-one class="org.hch.yhw.auction.model.AuctionUser"
   lazy="false" name="winer">
   <column name="winer_id"/>
  </many-to-one>
  <many-to-one class="org.hch.yhw.auction.model.Kind" lazy="false" name="kind">
   <column name="kind_id"/>
  </many-to-one>
  <many-to-one class="org.hch.yhw.auction.model.Bigkind" fetch="select" name="bigkind">
   <column name="bigkind_id"/>
  </many-to-one>
  <property  lazy="false" name="itemRemark" type="string">
   <column length="50" name="item_remark"/>
  </property>
  <property  lazy="false" name="itemName" type="string">
   <column length="50" name="item_name"/>
  </property>
  <property  lazy="false" name="itemDesc" type="string">
   <column length="200" name="item_desc"/>
  </property>
  <property  lazy="false" name="addtime" type="timestamp">
   <column length="19" name="addtime"/>
  </property>
  <property  lazy="false" name="endtime" type="timestamp">
   <column length="19" name="endtime"/>
  </property>
  <property  lazy="false" name="initPrice" type="double">
   <column length="12" name="init_price"/>
  </property>
  <property  lazy="false" name="maxPrice" type="double">
   <column length="12" name="max_price"/>
  </property>
 <property  lazy="false" name="zengfu" type="float">
 <column name="zengfu"/>
 </property>  
  <property  lazy="false" name="picname" type="string">
   <column name="picname"/>
  </property>
  <set inverse="true" name="bids" sort="unsorted">
   <key>
    <column name="item_id"/>
   </key>
   <one-to-many class="org.hch.yhw.auction.model.Bid"/>
  </set>
         <set name="orderis" inverse="true">
            <key>
                <column name="item_id" not-null="true" />
            </key>
            <one-to-many class="org.hch.yhw.auction.model.Orderi" />
        </set>
 </class>
</hibernate-mapping>
